.gitignore
LICENSE
README.rst
setup.py
beanbag/__init__.py
beanbag/attrdict.py
beanbag/auth.py
beanbag/bbexcept.py
beanbag/namespace.py
beanbag/url_v1.py
beanbag/v1.py
beanbag/v2.py
beanbag.egg-info/PKG-INFO
beanbag.egg-info/SOURCES.txt
beanbag.egg-info/dependency_links.txt
beanbag.egg-info/requires.txt
beanbag.egg-info/top_level.txt
debian/changelog
debian/compat
debian/control
debian/copyright
debian/python-beanbag-doc.install
debian/rules
debian/source/format
docs/Makefile
docs/attrdict.rst
docs/auth.rst
docs/conf.py
docs/examples.rst
docs/index.rst
docs/make.bat
docs/namespace.rst
docs/v1.rst
docs/v2.rst
examples/github
examples/twitter
tests/fake_req.py
tests/test_attrdict.py
tests/test_bbv1.py
tests/test_bbv2.py